MANIFEST.in
README.md
VERSION
pyproject.toml
setup.py
docs/source/description.rst
src/translucent/__init__.py
src/translucent/base.py
src/translucent/formatters.py
src/translucent/utils.py
translucent.egg-info/PKG-INFO
translucent.egg-info/SOURCES.txt
translucent.egg-info/dependency_links.txt
translucent.egg-info/requires.txt
translucent.egg-info/top_level.txt