Metadata-Version: 1.1
Name: translucent
Version: 0.4.1
Summary: UNKNOWN
Home-page: https://gitlab.com/greenhousegroup/ai/libraries/translucent/
Author: Greenhouse AI team
Author-email: ai@greenhousegroup.com
License: UNKNOWN
Platform: UNKNOWN
Classifier: Programming Language :: Python :: 3
Classifier: License :: OSI Approved :: MIT License
Classifier: Operating System :: OS Independent
Classifier: Programming Language :: Python :: 3
